{
    "loot": {
        "any": { "min": 1, "max": 3 }
    },
    "loot_view_distance": 3,
    "cost": {
        "cost": 3,
        "property": "stamina"
    },
    "hero_view": {
        "atlas": "atlases/gameplay.json",
        "idle_anim": "hero_idle",
        "left_anim": "hero_left",
        "up_anim": "hero_up",
        "right_anim": "hero_right",
        "down_anim": "hero_down"
    },
    "field_size": {
        "min_x": -4,
        "max_x": 4,
        "min_y": -4,
        "max_y": 4
    },
    "fog_view": {
        "atlas": "atlases/gameplay.json",
        "sprite": "hidden_loot"
    },
    "openable_view": {
        "atlas": "atlases/gameplay.json",
        "l": "openable_l",
        "u": "openable_u",
        "r": "openable_r",
        "d": "openable_d"
    },
    "tiles": [
        {
            "weight": 1,
            "atlas": "atlases/gameplay.json",
            "sprite": "tile_lurd",
            "connections": [
                "UP",
                "LEFT",
                "DOWN",
                "RIGHT"
            ]
        },
        {
            "weight": 1,
            "atlas": "atlases/gameplay.json",
            "sprite": "tile_lu",
            "connections": [
                "UP",
                "LEFT"
            ]
        },
        {
            "weight": 1,
            "atlas": "atlases/gameplay.json",
            "sprite": "tile_lr",
            "connections": [
                "LEFT",
                "RIGHT"
            ]
        },
        {
            "weight": 1,
            "atlas": "atlases/gameplay.json",
            "sprite": "tile_ld",
            "connections": [
                "LEFT",
                "DOWN"
            ]
        },
        {
            "weight": 1,
            "atlas": "atlases/gameplay.json",
            "sprite": "tile_ur",
            "connections": [
                "UP",
                "RIGHT"
            ]
        },
        {
            "weight": 1,
            "atlas": "atlases/gameplay.json",
            "sprite": "tile_ud",
            "connections": [
                "UP",
                "DOWN"
            ]
        },
        {
            "weight": 1,
            "atlas": "atlases/gameplay.json",
            "sprite": "tile_rd",
            "connections": [
                "DOWN",
                "RIGHT"
            ]
        },
        {
            "weight": 1,
            "atlas": "atlases/gameplay.json",
            "sprite": "tile_urd",
            "connections": [
                "UP",
                "DOWN",
                "RIGHT"
            ]
        },
        {
            "weight": 1,
            "atlas": "atlases/gameplay.json",
            "sprite": "tile_lrd",
            "connections": [
                "LEFT",
                "DOWN",
                "RIGHT"
            ]
        },
        {
            "weight": 1,
            "atlas": "atlases/gameplay.json",
            "sprite": "tile_lud",
            "connections": [
                "UP",
                "LEFT",
                "DOWN"
            ]
        },
        {
            "weight": 1,
            "atlas": "atlases/gameplay.json",
            "sprite": "tile_lur",
            "connections": [
                "UP",
                "LEFT",
                "RIGHT"
            ]
        },
        {
            "weight": 1,
            "atlas": "atlases/gameplay.json",
            "sprite": "tile_l",
            "connections": [
                "LEFT"
            ]
        },
        {
            "weight": 1,
            "atlas": "atlases/gameplay.json",
            "sprite": "tile_u",
            "connections": [
                "UP"
            ]
        },
        {
            "weight": 1,
            "atlas": "atlases/gameplay.json",
            "sprite": "tile_r",
            "connections": [
                "RIGHT"
            ]
        },
        {
            "weight": 1,
            "atlas": "atlases/gameplay.json",
            "sprite": "tile_d",
            "connections": [
                "DOWN"
            ]
        }
    ]
}